[
  {
    "url": "/103886/",
    "raw_response": "- 0 表示正常URL\n\nURL: /103886 是一个合法的Web请求，符合标准的HTTP请求格式，且没有包含任何恶意攻击特征。",
    "elapsed_time_sec": 1.332,
    "rule_prediction": "0",
    "rule_matched": [],
    "rule_summary": "规则引擎未检测到异常",
    "model_prediction": "0",
    "model_reason": "- 0 表示正常URL\n\nURL: /103886 是一个合法的Web请求，符合标准的HTTP请求格式，且没有包含任何恶意攻击特征。",
    "predicted": "0",
    "reason": "[规则通过] 规则引擎未检测到异常 | [模型判断] - 0 表示正常URL\n\nURL: /103886 是一个合法的Web请求，符合标准的HTTP请求格式，且没有包含任何恶意攻击特征。",
    "true_label": "0"
  },
  {
    "url": "/rcanimal/",
    "raw_response": "- 0 表示正常URL\n\nURL: /rcanimal/ 是一个合法的Web请求，符合标准的HTTP请求格式，没有包含任何恶意攻击特征。",
    "elapsed_time_sec": 1.105,
    "rule_prediction": "0",
    "rule_matched": [],
    "rule_summary": "规则引擎未检测到异常",
    "model_prediction": "0",
    "model_reason": "- 0 表示正常URL\n\nURL: /rcanimal/ 是一个合法的Web请求，符合标准的HTTP请求格式，没有包含任何恶意攻击特征。",
    "predicted": "0",
    "reason": "[规则通过] 规则引擎未检测到异常 | [模型判断] - 0 表示正常URL\n\nURL: /rcanimal/ 是一个合法的Web请求，符合标准的HTTP请求格式，没有包含任何恶意攻击特征。",
    "true_label": "0"
  },
  {
    "url": "/458010b88d9ce/",
    "raw_response": "- 0 表示正常URL\n\nURL: /458010b88d9ce/ 是正常URL，没有包含任何恶意攻击特征。",
    "elapsed_time_sec": 1.096,
    "rule_prediction": "0",
    "rule_matched": [],
    "rule_summary": "规则引擎未检测到异常",
    "model_prediction": "0",
    "model_reason": "- 0 表示正常URL\n\nURL: /458010b88d9ce/ 是正常URL，没有包含任何恶意攻击特征。",
    "predicted": "0",
    "reason": "[规则通过] 规则引擎未检测到异常 | [模型判断] - 0 表示正常URL\n\nURL: /458010b88d9ce/ 是正常URL，没有包含任何恶意攻击特征。",
    "true_label": "0"
  },
  {
    "url": "/cclogovs/",
    "raw_response": "- 0 表示正常URL\n\nURL: /cclogovs/ 是一个合法的Web请求，符合标准的HTTP请求格式，且没有包含任何恶意攻击特征。",
    "elapsed_time_sec": 1.172,
    "rule_prediction": "0",
    "rule_matched": [],
    "rule_summary": "规则引擎未检测到异常",
    "model_prediction": "0",
    "model_reason": "- 0 表示正常URL\n\nURL: /cclogovs/ 是一个合法的Web请求，符合标准的HTTP请求格式，且没有包含任何恶意攻击特征。",
    "predicted": "0",
    "reason": "[规则通过] 规则引擎未检测到异常 | [模型判断] - 0 表示正常URL\n\nURL: /cclogovs/ 是一个合法的Web请求，符合标准的HTTP请求格式，且没有包含任何恶意攻击特征。",
    "true_label": "0"
  },
  {
    "url": "/using-localization/",
    "raw_response": "- 0 表示正常URL\n\nURL: /using-localization 是一个合法的Web请求，符合标准的HTTP请求格式，没有包含任何恶意攻击特征。",
    "elapsed_time_sec": 1.034,
    "rule_prediction": "0",
    "rule_matched": [],
    "rule_summary": "规则引擎未检测到异常",
    "model_prediction": "0",
    "model_reason": "- 0 表示正常URL\n\nURL: /using-localization 是一个合法的Web请求，符合标准的HTTP请求格式，没有包含任何恶意攻击特征。",
    "predicted": "0",
    "reason": "[规则通过] 规则引擎未检测到异常 | [模型判断] - 0 表示正常URL\n\nURL: /using-localization 是一个合法的Web请求，符合标准的HTTP请求格式，没有包含任何恶意攻击特征。",
    "true_label": "0"
  },
  {
    "url": "/121006_dakotacwpressconf/",
    "raw_response": "- 0 表示正常URL\n\nURL: /121006_dakotacwpressconf/ 是一个合法的Web请求，符合正常请求特征。没有包含任何恶意攻击特征，例如SQL注入、XSS、命令执行、路径遍历等。因此，该URL是安全的。",
    "elapsed_time_sec": 1.918,
    "rule_prediction": "0",
    "rule_matched": [],
    "rule_summary": "规则引擎未检测到异常",
    "model_prediction": "0",
    "model_reason": "- 0 表示正常URL\n\nURL: /121006_dakotacwpressconf/ 是一个合法的Web请求，符合正常请求特征。没有包含任何恶意攻击特征，例如SQL注入、XSS、命令执行、路径遍历等。因此，该URL是安全的。",
    "predicted": "0",
    "reason": "[规则通过] 规则引擎未检测到异常 | [模型判断] - 0 表示正常URL\n\nURL: /121006_dakotacwpressconf/ 是一个合法的Web请求，符合正常请求特征。没有包含任何恶意攻击特征，例如SQL注入、XSS、命令执行、路径遍历等。因此，该URL是安全的。",
    "true_label": "0"
  },
  {
    "url": "/50393994/",
    "raw_response": "- 0 表示正常URL\n\nURL: /50393994 是一个合法的Web请求，符合正常请求特征。没有包含任何恶意攻击特征，例如SQL注入、XSS、命令执行、路径遍历等。该URL的结构和内容也符合标准的HTTP请求格式。",
    "elapsed_time_sec": 1.934,
    "rule_prediction": "0",
    "rule_matched": [],
    "rule_summary": "规则引擎未检测到异常",
    "model_prediction": "0",
    "model_reason": "- 0 表示正常URL\n\nURL: /50393994 是一个合法的Web请求，符合正常请求特征。没有包含任何恶意攻击特征，例如SQL注入、XSS、命令执行、路径遍历等。该URL的结构和内容也符合标准的HTTP请求格式。",
    "predicted": "0",
    "reason": "[规则通过] 规则引擎未检测到异常 | [模型判断] - 0 表示正常URL\n\nURL: /50393994 是一个合法的Web请求，符合正常请求特征。没有包含任何恶意攻击特征，例如SQL注入、XSS、命令执行、路径遍历等。该URL的结构和内容也符合标准的HTTP请求格式。",
    "true_label": "0"
  },
  {
    "url": "/169393/",
    "raw_response": "- 0 表示正常URL\n\nURL: /169393 是一个合法的Web请求，符合标准的HTTP请求格式，且没有包含任何恶意攻击特征。",
    "elapsed_time_sec": 1.133,
    "rule_prediction": "0",
    "rule_matched": [],
    "rule_summary": "规则引擎未检测到异常",
    "model_prediction": "0",
    "model_reason": "- 0 表示正常URL\n\nURL: /169393 是一个合法的Web请求，符合标准的HTTP请求格式，且没有包含任何恶意攻击特征。",
    "predicted": "0",
    "reason": "[规则通过] 规则引擎未检测到异常 | [模型判断] - 0 表示正常URL\n\nURL: /169393 是一个合法的Web请求，符合标准的HTTP请求格式，且没有包含任何恶意攻击特征。",
    "true_label": "0"
  },
  {
    "url": "/166636/",
    "raw_response": "- 0 表示正常URL\n\nURL: /166636 是一个合法的Web请求，符合标准的HTTP请求格式，且没有包含任何恶意攻击特征。",
    "elapsed_time_sec": 1.149,
    "rule_prediction": "0",
    "rule_matched": [],
    "rule_summary": "规则引擎未检测到异常",
    "model_prediction": "0",
    "model_reason": "- 0 表示正常URL\n\nURL: /166636 是一个合法的Web请求，符合标准的HTTP请求格式，且没有包含任何恶意攻击特征。",
    "predicted": "0",
    "reason": "[规则通过] 规则引擎未检测到异常 | [模型判断] - 0 表示正常URL\n\nURL: /166636 是一个合法的Web请求，符合标准的HTTP请求格式，且没有包含任何恶意攻击特征。",
    "true_label": "0"
  },
  {
    "url": "/labview_v2/",
    "raw_response": "- 0 表示正常URL\n\nURL: /labview_v2 是一个合法的Web请求，符合正常请求特征，没有包含任何恶意攻击特征。",
    "elapsed_time_sec": 1.019,
    "rule_prediction": "0",
    "rule_matched": [],
    "rule_summary": "规则引擎未检测到异常",
    "model_prediction": "0",
    "model_reason": "- 0 表示正常URL\n\nURL: /labview_v2 是一个合法的Web请求，符合正常请求特征，没有包含任何恶意攻击特征。",
    "predicted": "0",
    "reason": "[规则通过] 规则引擎未检测到异常 | [模型判断] - 0 表示正常URL\n\nURL: /labview_v2 是一个合法的Web请求，符合正常请求特征，没有包含任何恶意攻击特征。",
    "true_label": "0"
  },
  {
    "url": "/top.php?stuff='uname >q36497765 #",
    "raw_response": "- 1 表示异常URL  \n- 判定理由: 包含了SQL注入特征，具体为 `'uname >q36497765 #` 中的 `'` 和 `#`，这属于SQL注入攻击。",
    "elapsed_time_sec": 1.587,
    "rule_prediction": "0",
    "rule_matched": [],
    "rule_summary": "规则引擎未检测到异常",
    "model_prediction": "1",
    "model_reason": "包含了SQL注入特征，具体为 `'uname >q36497765 #` 中的 `'` 和 `#`，这属于SQL注入攻击。",
    "predicted": "1",
    "reason": "[规则通过] 规则引擎未检测到异常 | [模型判断] 包含了SQL注入特征，具体为 `'uname >q36497765 #` 中的 `'` 和 `#`，这属于SQL注入攻击。",
    "true_label": "1"
  },
  {
    "url": "/h21y8w52.nsf?<script>cross_site_scripting.nasl</script>",
    "raw_response": "1\n- 这个URL包含恶意脚本，具体攻击类型为XSS（跨站脚本攻击），恶意特征包括`<script>`标签。",
    "elapsed_time_sec": 0.973,
    "rule_prediction": "1",
    "rule_matched": [
      {
        "rule_id": "XSS_001",
        "rule_name": "XSS - Script标签",
        "attack_type": "xss",
        "severity": "high",
        "matched_text": "<script>",
        "description": "检测到script标签XSS尝试"
      }
    ],
    "rule_summary": "规则引擎检测到 1 条匹配规则: 攻击类型包括 xss; 严重程度: 高",
    "model_prediction": "1",
    "model_reason": "这个URL包含恶意脚本，具体攻击类型为XSS（跨站脚本攻击），恶意特征包括`<script>`标签。",
    "predicted": "1",
    "reason": "[规则匹配] 规则引擎检测到 1 条匹配规则: 攻击类型包括 xss; 严重程度: 高 | [模型判断] 这个URL包含恶意脚本，具体攻击类型为XSS（跨站脚本攻击），恶意特征包括`<script>`标签。",
    "true_label": "1"
  },
  {
    "url": "/ca000001.pl?action=showcart&hop=\\\"><script>alert('vulnerable')</script>&path=acatalog/",
    "raw_response": "1\n异常URL\n\n判断理由：该URL包含恶意特征，具体为XSS跨站脚本攻击。恶意特征包括 `<script>` 标签，该标签包含恶意代码，可能导致用户被恶意脚本欺骗。",
    "elapsed_time_sec": 1.378,
    "rule_prediction": "1",
    "rule_matched": [
      {
        "rule_id": "XSS_001",
        "rule_name": "XSS - Script标签",
        "attack_type": "xss",
        "severity": "high",
        "matched_text": "<script>",
        "description": "检测到script标签XSS尝试"
      }
    ],
    "rule_summary": "规则引擎检测到 1 条匹配规则: 攻击类型包括 xss; 严重程度: 高",
    "model_prediction": "1",
    "model_reason": "异常URL\n\n判断理由：该URL包含恶意特征，具体为XSS跨站脚本攻击。恶意特征包括 `<script>` 标签，该标签包含恶意代码，可能导致用户被恶意脚本欺骗。",
    "predicted": "1",
    "reason": "[规则匹配] 规则引擎检测到 1 条匹配规则: 攻击类型包括 xss; 严重程度: 高 | [模型判断] 异常URL\n\n判断理由：该URL包含恶意特征，具体为XSS跨站脚本攻击。恶意特征包括 `<script>` 标签，该标签包含恶意代码，可能导致用户被恶意脚本欺骗。",
    "true_label": "1"
  },
  {
    "url": "/scripts/edit_image.php?dn=1&userfile=/etc/passwd&userfile_name= ;id;",
    "raw_response": "- 1 表示异常URL  \n- 判定理由: 包含了SQL注入、命令执行和文件包含等恶意特征。具体攻击类型包括：SQL注入（`'`、`--`、`#`、`union`、`select`等），命令注入（`|`、`;`、`&&`、shell命令等），以及文件包含（`/etc/passwd`）。这些特征表明该URL存在潜在的安全风险。",
    "elapsed_time_sec": 2.76,
    "rule_prediction": "0",
    "rule_matched": [],
    "rule_summary": "规则引擎未检测到异常",
    "model_prediction": "1",
    "model_reason": "包含了SQL注入、命令执行和文件包含等恶意特征。具体攻击类型包括：SQL注入（`'`、`--`、`#`、`union`、`select`等），命令注入（`|`、`;`、`&&`、shell命令等），以及文件包含（`/etc/passwd`）。这些特征表明该URL存在潜在的安全风险。",
    "predicted": "1",
    "reason": "[规则通过] 规则引擎未检测到异常 | [模型判断] 包含了SQL注入、命令执行和文件包含等恶意特征。具体攻击类型包括：SQL注入（`'`、`--`、`#`、`union`、`select`等），命令注入（`|`、`;`、`&&`、shell命令等），以及文件包含（`/etc/passwd`）。这些特征表明该URL存在潜在的安全风险。",
    "true_label": "1"
  },
  {
    "url": "/javascript/mta.exe",
    "raw_response": "- 1 表示异常URL  \n- 判定理由: 包含了JavaScript代码，这属于XSS攻击特征，且包含`javascript:`，属于跨站脚本攻击。",
    "elapsed_time_sec": 1.173,
    "rule_prediction": "0",
    "rule_matched": [],
    "rule_summary": "规则引擎未检测到异常",
    "model_prediction": "1",
    "model_reason": "包含了JavaScript代码，这属于XSS攻击特征，且包含`javascript:`，属于跨站脚本攻击。",
    "predicted": "1",
    "reason": "[规则通过] 规则引擎未检测到异常 | [模型判断] 包含了JavaScript代码，这属于XSS攻击特征，且包含`javascript:`，属于跨站脚本攻击。",
    "true_label": "1"
  },
  {
    "url": "/examples/jsp/colors/kernel/loadkernel.php?installpath=/etc/passwd\\x00",
    "raw_response": "- 1 表示异常URL  \n- 判定理由: 包含了恶意特征 `include`、`/etc/passwd` 和 `xml`，这些特征属于文件包含攻击，可能被用来执行远程代码或窃取敏感信息。",
    "elapsed_time_sec": 1.528,
    "rule_prediction": "0",
    "rule_matched": [],
    "rule_summary": "规则引擎未检测到异常",
    "model_prediction": "1",
    "model_reason": "包含了恶意特征 `include`、`/etc/passwd` 和 `xml`，这些特征属于文件包含攻击，可能被用来执行远程代码或窃取敏感信息。",
    "predicted": "1",
    "reason": "[规则通过] 规则引擎未检测到异常 | [模型判断] 包含了恶意特征 `include`、`/etc/passwd` 和 `xml`，这些特征属于文件包含攻击，可能被用来执行远程代码或窃取敏感信息。",
    "true_label": "1"
  },
  {
    "url": "/examples/jsp/cal/feedsplitter.php?format=../../../../../../../../../../etc/passwd\\x00&debug=1",
    "raw_response": "- 1 表示异常URL\n\n具体的攻击类型和恶意特征：\n- 命令注入：包含 `../../../../../../../../../../etc/passwd`，这是一个典型的路径遍历攻击，可以执行远程代码。\n- 文件包含：包含 `../../../../../../../../../../etc/passwd`，这是一个典型的文件包含攻击，可以读取远程文件内容。",
    "elapsed_time_sec": 2.036,
    "rule_prediction": "0",
    "rule_matched": [],
    "rule_summary": "规则引擎未检测到异常",
    "model_prediction": "1",
    "model_reason": "- 1 表示异常URL\n\n具体的攻击类型和恶意特征：\n- 命令注入：包含 `../../../../../../../../../../etc/passwd`，这是一个典型的路径遍历攻击，可以执行远程代码。\n- 文件包含：包含 `../../../../../../../../../../etc/passwd`，这是一个典型的文件包含攻击，可以读取远程文件内容。",
    "predicted": "1",
    "reason": "[规则通过] 规则引擎未检测到异常 | [模型判断] - 1 表示异常URL\n\n具体的攻击类型和恶意特征：\n- 命令注入：包含 `../../../../../../../../../../etc/passwd`，这是一个典型的路径遍历攻击，可以执行远程代码。\n- 文件包含：包含 `../../../../../../../../../../etc/passwd`，这是一个典型的文件包含攻击，可以读取远程文件内容。",
    "true_label": "1"
  },
  {
    "url": "/phpwebfilemgr/index.php?f=../../../../../../../../../etc/passwd",
    "raw_response": "- 1 表示异常URL  \n- 判定理由: 包含了路径遍历特征，具体为 `/phpwebfilemgr/index.php?f=../../../../../../../../../etc/passwd`，该路径访问了 `/etc/passwd`，这属于典型的恶意攻击特征，特别是路径遍历攻击。",
    "elapsed_time_sec": 1.872,
    "rule_prediction": "0",
    "rule_matched": [],
    "rule_summary": "规则引擎未检测到异常",
    "model_prediction": "1",
    "model_reason": "包含了路径遍历特征，具体为 `/phpwebfilemgr/index.php?f=../../../../../../../../../etc/passwd`，该路径访问了 `/etc/passwd`，这属于典型的恶意攻击特征，特别是路径遍历攻击。",
    "predicted": "1",
    "reason": "[规则通过] 规则引擎未检测到异常 | [模型判断] 包含了路径遍历特征，具体为 `/phpwebfilemgr/index.php?f=../../../../../../../../../etc/passwd`，该路径访问了 `/etc/passwd`，这属于典型的恶意攻击特征，特别是路径遍历攻击。",
    "true_label": "1"
  },
  {
    "url": "/cgi-bin/script/cat_for_gen.php?ad=1&ad_direct=../&m_for_racine=</option></select><?phpinfo();?>",
    "raw_response": "- 1 表示异常URL\n\n具体的攻击类型和恶意特征：\n- 路径遍历：包含 `../`，这是一个典型的路径遍历攻击特征。\n- 其他恶意特征：包含 `</option>` 和 `<?phpinfo();`，这些特征也属于恶意攻击的范畴。",
    "elapsed_time_sec": 1.845,
    "rule_prediction": "0",
    "rule_matched": [],
    "rule_summary": "规则引擎未检测到异常",
    "model_prediction": "1",
    "model_reason": "- 1 表示异常URL\n\n具体的攻击类型和恶意特征：\n- 路径遍历：包含 `../`，这是一个典型的路径遍历攻击特征。\n- 其他恶意特征：包含 `</option>` 和 `<?phpinfo();`，这些特征也属于恶意攻击的范畴。",
    "predicted": "1",
    "reason": "[规则通过] 规则引擎未检测到异常 | [模型判断] - 1 表示异常URL\n\n具体的攻击类型和恶意特征：\n- 路径遍历：包含 `../`，这是一个典型的路径遍历攻击特征。\n- 其他恶意特征：包含 `</option>` 和 `<?phpinfo();`，这些特征也属于恶意攻击的范畴。",
    "true_label": "1"
  },
  {
    "url": "/examples/jsp/cal/search.php?allwords=<br><script>foo</script>&cid=0&title=1&desc=1",
    "raw_response": "- 1 表示异常URL  \n- 判定理由: 包含了SQL注入、XSS和命令执行的恶意特征。具体攻击类型包括：  \n  - SQL注入：`<br>` 和 `script` 语句  \n  - XSS：`<script>` 语句  \n  - 命令执行：`script` 语句  \n  - 其他恶意特征：`<br>` 和 `script` 语句",
    "elapsed_time_sec": 2.81,
    "rule_prediction": "1",
    "rule_matched": [
      {
        "rule_id": "XSS_001",
        "rule_name": "XSS - Script标签",
        "attack_type": "xss",
        "severity": "high",
        "matched_text": "<script>",
        "description": "检测到script标签XSS尝试"
      }
    ],
    "rule_summary": "规则引擎检测到 1 条匹配规则: 攻击类型包括 xss; 严重程度: 高",
    "model_prediction": "1",
    "model_reason": "包含了SQL注入、XSS和命令执行的恶意特征。具体攻击类型包括：  \n  - SQL注入：`<br>` 和 `script` 语句  \n  - XSS：`<script>` 语句  \n  - 命令执行：`script` 语句  \n  - 其他恶意特征：`<br>` 和 `script` 语句",
    "predicted": "1",
    "reason": "[规则匹配] 规则引擎检测到 1 条匹配规则: 攻击类型包括 xss; 严重程度: 高 | [模型判断] 包含了SQL注入、XSS和命令执行的恶意特征。具体攻击类型包括：  \n  - SQL注入：`<br>` 和 `script` 语句  \n  - XSS：`<script>` 语句  \n  - 命令执行：`script` 语句  \n  - 其他恶意特征：`<br>` 和 `script` 语句",
    "true_label": "1"
  }
]